EasySeaborn/__init__.py
EasySeaborn/bar.py
EasySeaborn/box.py
EasySeaborn/count.py
EasySeaborn/ecdf.py
EasySeaborn/facet.py
EasySeaborn/fit.py
EasySeaborn/heat.py
EasySeaborn/hist.py
EasySeaborn/jitter.py
EasySeaborn/joint.py
EasySeaborn/kde.py
EasySeaborn/line.py
EasySeaborn/matrix.py
EasySeaborn/point.py
EasySeaborn/resid.py
EasySeaborn/scatter.py
EasySeaborn/violin.py
EasySeaborn/fonts/FZSTK.TTF
EasySeaborn/fonts/FZYTK.TTF
EasySeaborn/fonts/SIMLI.TTF
EasySeaborn/fonts/SIMYOU.TTF
EasySeaborn/fonts/STCAIYUN.TTF
EasySeaborn/fonts/STFANGSO.TTF
EasySeaborn/fonts/STHUPO.TTF
EasySeaborn/fonts/STKAITI.TTF
EasySeaborn/fonts/STLITI.TTF
EasySeaborn/fonts/STSONG.TTF
EasySeaborn/fonts/STXIHEI.TTF
EasySeaborn/fonts/STXINGKA.TTF
EasySeaborn/fonts/STXINWEI.TTF
EasySeaborn/fonts/STZHONGS.TTF
EasySeaborn/fonts/arial.ttf
EasySeaborn/fonts/msyhl.ttc
EasySeaborn/fonts/simfang.ttf
EasySeaborn/fonts/simhei.ttf
EasySeaborn/fonts/simkai.ttf
EasySeaborn/fonts/simsun.ttc
EasySeaborn/fonts/times.ttf
easyseaborn-0.0.4.dist-info/METADATA
easyseaborn-0.0.4.dist-info/WHEEL
easyseaborn-0.0.4.dist-info/licenses/LICENSE
easyseaborn-0.0.4.dist-info/RECORD
